cyberfusion/ProftpdSupport/__init__.py
cyberfusion/ProftpdSupport/database.py
cyberfusion/ProftpdSupport/models.py
cyberfusion/ProftpdSupport/settings.py
cyberfusion/ProftpdSupport/users.py
python3_cyberfusion_proftpd_support-1.1.dist-info/METADATA
python3_cyberfusion_proftpd_support-1.1.dist-info/WHEEL
python3_cyberfusion_proftpd_support-1.1.dist-info/entry_points.txt
python3_cyberfusion_proftpd_support-1.1.dist-info/top_level.txt
python3_cyberfusion_proftpd_support-1.1.dist-info/RECORD
