Metadata-Version: 2.4
Name: python3-cyberfusion-proftpd-support
Version: 1.1
Summary: Library to manage ProFTPD.
Author-email: Cyberfusion <support@cyberfusion.io>
Project-URL: Source, https://github.com/CyberfusionIO/python3-cyberfusion-proftpd-support
Requires-Dist: pydantic-settings==2.8.1
